slurpit_netbox/__init__.py
slurpit_netbox/api/__init__.py
slurpit_netbox/api/serializers.py
slurpit_netbox/api/urls.py
slurpit_netbox/api/views.py
slurpit_netbox/decorators.py
slurpit_netbox/filtersets.py
slurpit_netbox/forms.py
slurpit_netbox/importer.py
slurpit_netbox/management/__init__.py
slurpit_netbox/management/choices.py
slurpit_netbox/migrations/0001_initial.py
slurpit_netbox/migrations/0002_alter_slurpitplanning_name_and_more.py
slurpit_netbox/migrations/0003_alter_slurpitimporteddevice_ipv4_and_more.py
slurpit_netbox/migrations/0004_slurpitmapping.py
slurpit_netbox/migrations/0005_manufacturer.py
slurpit_netbox/migrations/0006_slurpitsnapshot_result_type.py
slurpit_netbox/migrations/0007_slurpitinitipaddress.py
slurpit_netbox/migrations/0008_slurpitinitipaddress_address_and_more.py
slurpit_netbox/migrations/0009_slurpitinterface.py
slurpit_netbox/migrations/0010_alter_slurpitinterface_name.py
slurpit_netbox/migrations/0011_alter_slurpitinterface_device.py
slurpit_netbox/migrations/0012_slurpitprefix.py
slurpit_netbox/migrations/0013_slurpitinitipaddress_ignore_status.py
slurpit_netbox/migrations/0014_slurpitinitipaddress_ignore_description_and_more.py
slurpit_netbox/migrations/0015_slurpitinterface_ignore_duplex_and_more.py
slurpit_netbox/migrations/0016_slurpitprefix_ignore_description_and_more.py
slurpit_netbox/migrations/0017_slurpitvlan_and_more.py
slurpit_netbox/migrations/0018_slurpitvlan_ignore_description_and_more.py
slurpit_netbox/migrations/0019_alter_slurpitvlan_name.py
slurpit_netbox/migrations/0020_alter_slurpitinitipaddress_ignore_description_and_more.py
slurpit_netbox/migrations/0021_slurpitimporteddevice_site_slurpitstageddevice_site.py
slurpit_netbox/migrations/0022_delete_slurpitlog.py
slurpit_netbox/migrations/0023_alter_slurpitinterface_cable_end.py
slurpit_netbox/migrations/0024_alter_slurpitprefix_scope.py
slurpit_netbox/migrations/0025_alter_slurpitprefix_site_rename.py
slurpit_netbox-1.2.7.dist-info/METADATA
slurpit_netbox-1.2.7.dist-info/WHEEL
slurpit_netbox-1.2.7.dist-info/licenses/LICENSE
slurpit_netbox-1.2.7.dist-info/RECORD
