Metadata-Version: 2.4
Name: slurpit_netbox
Version: 1.2.7
Summary: 
License-File: LICENSE
Author: Pieter
Author-email: pieter@slurpit.io
Requires-Python: >=3.10,<4.0
Classifier: Programming Language :: Python :: 3
Classifier: Programming Language :: Python :: 3.10
Classifier: Programming Language :: Python :: 3.11
Classifier: Programming Language :: Python :: 3.12
Classifier: Programming Language :: Python :: 3.13
Classifier: Programming Language :: Python :: 3.14
Requires-Dist: djangorestframework-bulk (>=0.2.1,<0.3.0)
Requires-Dist: requests (>=2.31.0,<3.0.0)
